{"seeds": [{"seed": 91, "data": {"data": [{"x": "15"}, {"x": "2"}, {"x": "8"}, {"x": "-12"}, {"x": "39"}, {"x": "-9"}, {"x": "23"}, {"x": "10"}, {"x": "25"}, {"x": "12"}, {"x": "-3"}, {"x": "31"}, {"x": "1"}, {"x": "26"}, {"x": "-15"}, {"x": "53"}, {"x": "48"}], "barx": "14.9411764705882", "med": "12", "mde": ["-15", "-12", "-9", "-3", "1", "2", "8", "10", "12", "15", "23", "25", "26", "31", "39", "48", "53"], "skew": "right skew", "n": "15", "sum": "254", "__seed__": "0091"}}, {"seed": 85, "data": {"data": [{"x": "20"}, {"x": "-5"}, {"x": "34"}, {"x": "34"}, {"x": "-7"}, {"x": "2"}, {"x": "24"}, {"x": "-4"}, {"x": "15"}, {"x": "-9"}, {"x": "17"}, {"x": "14"}, {"x": "66"}, {"x": "87"}], "barx": "20.5714285714286", "med": "16", "mde": ["34"], "skew": "right skew", "n": "12", "sum": "288", "__seed__": "0085"}}, {"seed": 108, "data": {"data": [{"x": "72"}, {"x": "70"}, {"x": "-35"}, {"x": "4"}, {"x": "-26"}, {"x": "21"}, {"x": "82"}, {"x": "61"}, {"x": "32"}, {"x": "14"}, {"x": "176"}, {"x": "97"}], "barx": "47.3333333333333", "med": "\\frac{93}{2}", "mde": ["-35", "-26", "4", "14", "21", "32", "61", "70", "72", "82", "97", "176"], "skew": "right skew", "n": "10", "sum": "568", "__seed__": "0108"}}, {"seed": 913, "data": {"data": [{"x": "92"}, {"x": "94"}, {"x": "103"}, {"x": "67"}, {"x": "75"}, {"x": "125"}, {"x": "93"}, {"x": "105"}, {"x": "86"}, {"x": "96"}, {"x": "94"}, {"x": "100"}, {"x": "99"}, {"x": "86"}, {"x": "37"}, {"x": "133"}], "barx": "92.8125000000000", "med": "94", "mde": ["86", "94"], "skew": "left skew", "n": "14", "sum": "1485", "__seed__": "0913"}}, {"seed": 114, "data": {"data": [{"x": "39"}, {"x": "42"}, {"x": "92"}, {"x": "34"}, {"x": "34"}, {"x": "68"}, {"x": "17"}, {"x": "74"}, {"x": "29"}, {"x": "37"}, {"x": "63"}, {"x": "65"}, {"x": "23"}, {"x": "40"}, {"x": "46"}, {"x": "-47"}, {"x": "159"}], "barx": "47.9411764705882", "med": "40", "mde": ["34"], "skew": "right skew", "n": "15", "sum": "815", "__seed__": "0114"}}, {"seed": 711, "data": {"data": [{"x": "81"}, {"x": "78"}, {"x": "72"}, {"x": "115"}, {"x": "70"}, {"x": "113"}, {"x": "66"}, {"x": "62"}, {"x": "99"}, {"x": "108"}, {"x": "49"}, {"x": "202"}, {"x": "-33"}], "barx": "83.2307692307692", "med": "78", "mde": ["-33", "49", "62", "66", "70", "72", "78", "81", "99", "108", "113", "115", "202"], "skew": "right skew", "n": "11", "sum": "1082", "__seed__": "0711"}}, {"seed": 352, "data": {"data": [{"x": "83"}, {"x": "87"}, {"x": "91"}, {"x": "106"}, {"x": "89"}, {"x": "86"}, {"x": "81"}, {"x": "77"}, {"x": "89"}, {"x": "86"}, {"x": "57"}, {"x": "92"}, {"x": "84"}, {"x": "138"}, {"x": "59"}], "barx": "87.0000000000000", "med": "86", "mde": ["86", "89"], "skew": "right skew", "n": "13", "sum": "1305", "__seed__": "0352"}}, {"seed": 242, "data": {"data": [{"x": "39"}, {"x": "134"}, {"x": "60"}, {"x": "66"}, {"x": "117"}, {"x": "42"}, {"x": "56"}, {"x": "70"}, {"x": "20"}, {"x": "46"}, {"x": "77"}, {"x": "73"}, {"x": "80"}, {"x": "187"}, {"x": "184"}], "barx": "83.4000000000000", "med": "70", "mde": ["20", "39", "42", "46", "56", "60", "66", "70", "73", "77", "80", "117", "134", "184", "187"], "skew": "right skew", "n": "13", "sum": "1251", "__seed__": "0242"}}, {"seed": 311, "data": {"data": [{"x": "65"}, {"x": "93"}, {"x": "66"}, {"x": "54"}, {"x": "57"}, {"x": "86"}, {"x": "71"}, {"x": "38"}, {"x": "60"}, {"x": "62"}, {"x": "73"}, {"x": "62"}, {"x": "79"}, {"x": "17"}, {"x": "10"}], "barx": "59.5333333333333", "med": "62", "mde": ["62"], "skew": "left skew", "n": "13", "sum": "893", "__seed__": "0311"}}, {"seed": 983, "data": {"data": [{"x": "84"}, {"x": "85"}, {"x": "115"}, {"x": "99"}, {"x": "106"}, {"x": "92"}, {"x": "46"}, {"x": "90"}, {"x": "85"}, {"x": "80"}, {"x": "114"}, {"x": "-10"}], "barx": "82.1666666666667", "med": "\\frac{175}{2}", "mde": ["85"], "skew": "left skew", "n": "10", "sum": "986", "__seed__": "0983"}}], "generated_on": "2023-01-21T23:22:16.069645+00:00"}