{"seeds": [{"seed": 283, "data": {"rat1": true, "Qt": "\\frac{5}{t^{3}}", "Qc": "\\frac{5}{c^{3}}", "factor": "c^{2} + c t + t^{2}", "n": "3", "nm1": "2", "twon": "6", "k": "5", "a": "1", "b": "2", "LB": "-12", "UB": "-\\frac{7}{64}", "LBk": "-60", "UBk": "-\\frac{35}{64}", "__seed__": "0283"}}, {"seed": 981, "data": {"poly1": true, "Qt": "3 \\, t^{4} - 2", "Qc": "3 \\, c^{4} - 2", "simp1": "3 \\, t^{4}", "simp2": "3 \\, c^{4}", "factor": "c^{3} + c^{2} t + c t^{2} + t^{3}", "n": "4", "nm1": "3", "k": "3", "a": "0", "b": "2", "LB": "0", "UB": "32", "LBk": "0", "UBk": "96", "__seed__": "0981"}}, {"seed": 59, "data": {"rat1": true, "Qt": "\\frac{4}{t^{2}}", "Qc": "\\frac{4}{c^{2}}", "factor": "c + t", "n": "2", "nm1": "1", "twon": "4", "k": "4", "a": "3", "b": "8", "LB": "-\\frac{16}{81}", "UB": "-\\frac{11}{4096}", "LBk": "-\\frac{64}{81}", "UBk": "-\\frac{11}{1024}", "__seed__": "0059"}}, {"seed": 865, "data": {"poly1": true, "Qt": "2 \\, t^{4} - 4", "Qc": "2 \\, c^{4} - 4", "simp1": "2 \\, t^{4}", "simp2": "2 \\, c^{4}", "factor": "c^{3} + c^{2} t + c t^{2} + t^{3}", "n": "4", "nm1": "3", "k": "2", "a": "0", "b": "1", "LB": "0", "UB": "4", "LBk": "0", "UBk": "8", "__seed__": "0865"}}, {"seed": 402, "data": {"rat1": true, "Qt": "\\frac{5}{t^{2}}", "Qc": "\\frac{5}{c^{2}}", "factor": "c + t", "n": "2", "nm1": "1", "twon": "4", "k": "5", "a": "1", "b": "6", "LB": "-12", "UB": "-\\frac{7}{1296}", "LBk": "-60", "UBk": "-\\frac{35}{1296}", "__seed__": "0402"}}, {"seed": 642, "data": {"hard1": true, "Qt": "\\frac{3}{\\sqrt{t + 2}}", "Qc": "\\frac{3}{\\sqrt{c + 2}}", "l": "2", "k": "3", "a": "1", "b": "4", "LB": "6 \\, \\sqrt{3}", "UB": "12 \\, \\sqrt{6}", "LBk": "-\\frac{1}{6} \\, \\sqrt{3}", "UBk": "-\\frac{1}{24} \\, \\sqrt{6}", "__seed__": "0642"}}, {"seed": 423, "data": {"rat1": true, "Qt": "\\frac{5}{t^{3}}", "Qc": "\\frac{5}{c^{3}}", "factor": "c^{2} + c t + t^{2}", "n": "3", "nm1": "2", "twon": "6", "k": "5", "a": "3", "b": "4", "LB": "-\\frac{16}{243}", "UB": "-\\frac{37}{4096}", "LBk": "-\\frac{80}{243}", "UBk": "-\\frac{185}{4096}", "__seed__": "0423"}}, {"seed": 283, "data": {"rat1": true, "Qt": "\\frac{5}{t^{3}}", "Qc": "\\frac{5}{c^{3}}", "factor": "c^{2} + c t + t^{2}", "n": "3", "nm1": "2", "twon": "6", "k": "5", "a": "1", "b": "2", "LB": "-12", "UB": "-\\frac{7}{64}", "LBk": "-60", "UBk": "-\\frac{35}{64}", "__seed__": "0283"}}, {"seed": 210, "data": {"hard1": true, "Qt": "\\frac{4}{\\sqrt{t + 4}}", "Qc": "\\frac{4}{\\sqrt{c + 4}}", "l": "4", "k": "4", "a": "-1", "b": "4", "LB": "6 \\, \\sqrt{3}", "UB": "32 \\, \\sqrt{2}", "LBk": "-\\frac{2}{9} \\, \\sqrt{3}", "UBk": "-\\frac{1}{16} \\, \\sqrt{2}", "__seed__": "0210"}}, {"seed": 570, "data": {"rat1": true, "Qt": "\\frac{2}{t^{4}}", "Qc": "\\frac{2}{c^{4}}", "factor": "c^{3} + c^{2} t + c t^{2} + t^{3}", "n": "4", "nm1": "3", "twon": "8", "k": "2", "a": "3", "b": "7", "LB": "-\\frac{1372}{6561}", "UB": "-\\frac{580}{5764801}", "LBk": "-\\frac{2744}{6561}", "UBk": "-\\frac{1160}{5764801}", "__seed__": "0570"}}], "generated_on": "2023-09-01T23:16:59.011109+00:00"}